argvard/__init__.py
argvard/_compat.py
argvard/exceptions.py
argvard/signature.py
argvard/utils.py
Argvard-0.3.0.dist-info/DESCRIPTION.rst
Argvard-0.3.0.dist-info/METADATA
Argvard-0.3.0.dist-info/pydist.json
Argvard-0.3.0.dist-info/RECORD
Argvard-0.3.0.dist-info/top_level.txt
Argvard-0.3.0.dist-info/WHEEL
