Metadata-Version: 2.0
Name: Argvard
Version: 0.3.0
Summary: Framework for command line applications
Home-page: https://github.com/DasIch/argvard
Author: Daniel Neuhäuser
Author-email: ich@danielneuhaeuser.de
License: Apache License, Version 2.0
Platform: UNKNOWN
Classifier: License :: OSI Approved :: Apache Software License
Classifier: Programming Language :: Python :: 2.7
Classifier: Programming Language :: Python :: 3.3
Classifier: Programming Language :: Python :: Implementation :: CPython
Classifier: Programming Language :: Python :: Implementation :: PyPy
